dotflz/__init__.py
dotflz/cli.py
dotflz/config.py
dotflz/config_item.py
dotflz/dotflz.py
dotflz/filesystem.py
dotflz-0.4.dist-info/LICENSE
dotflz-0.4.dist-info/METADATA
dotflz-0.4.dist-info/WHEEL
dotflz-0.4.dist-info/entry_points.txt
dotflz-0.4.dist-info/top_level.txt
dotflz-0.4.dist-info/RECORD
