Metadata-Version: 2.1
Name: dotflz
Version: 0.4
Summary: Utility to keep copies of dotfiles in one place
Home-page: https://github.com/ivanjermakov/dotflz
Author: Ivan Ermakov
Author-email: ivanjermakov1@gmail.com
License: MIT
Platform: UNKNOWN
Requires-Python: >=3
License-File: LICENSE
Requires-Dist: wheel
Requires-Dist: pyyaml
Requires-Dist: glob2
Requires-Dist: more-itertools
Requires-Dist: datetime
Requires-Dist: click
